iam/__init__.py
iam/pgiam.py
iam/tests.py
pypg_iam-0.7.8.dist-info/METADATA
pypg_iam-0.7.8.dist-info/WHEEL
pypg_iam-0.7.8.dist-info/RECORD
