Metadata-Version: 2.4
Name: pypg-iam
Version: 0.7.8
Summary: Python package for interacting with pg-iam
License: BSD-3-Clause
Author: Leon du Toit
Author-email: l.c.d.toit@usit.uio.no
Requires-Python: >=3.9,<4.0
Classifier: License :: OSI Approved :: BSD License
Classifier: Programming Language :: Python :: 3
Classifier: Programming Language :: Python :: 3.9
Classifier: Programming Language :: Python :: 3.10
Classifier: Programming Language :: Python :: 3.11
Classifier: Programming Language :: Python :: 3.12
Classifier: Programming Language :: Python :: 3.13
Classifier: Programming Language :: Python :: 3.14
Requires-Dist: psycopg2 (>=2.8.3,<3.0.0)
Requires-Dist: sqlalchemy (>=1.4.22,<2)
Project-URL: Repository, https://github.com/unioslo/pypg-iam
